<?xml version="1.0"?>
<!DOCTYPE I2CEConfiguration SYSTEM "I2CE_Configuration.dtd">
<I2CEConfiguration name="CustomReports-full-followup_clients">
  <metadata>
    <displayName>Relationship: followup_clients</displayName>
    <description>Relationship 'followup_clients' and all reports and report views.</description>
    <version>4.0.11.2014.08.14</version>
  </metadata>
  <configurationGroup name="CustomReports-full-followup_clients" path="/modules/CustomReports">
    <configurationGroup name="followup_clients" path="//modules/CustomReports/relationships/followup_clients">
      <displayName>Export</displayName>
      <configuration name="description" locale="en_US">
        <displayName>Description</displayName>
        <value>Followup Clients</value>
      </configuration>
      <configuration name="display_name" locale="en_US">
        <displayName>Display Name</displayName>
        <value>Followup Clients</value>
      </configuration>
      <configuration name="form">
        <displayName>Form</displayName>
        <value>person</value>
      </configuration>
      <configurationGroup name="joins">
        <displayName>Joins</displayName>
        <configurationGroup name="facility">
          <displayName>Facility</displayName>
          <configuration name="display_name" locale="en_US">
            <displayName>Display Name</displayName>
            <value>Facility</value>
          </configuration>
          <configuration name="form">
            <displayName>Form</displayName>
            <value>facility</value>
          </configuration>
          <configurationGroup name="join_data">
            <displayName>Join Data</displayName>
            <configuration name="field">
              <displayName>Field</displayName>
              <value>facility</value>
            </configuration>
          </configurationGroup>
          <configuration name="join_style">
            <displayName>Join Style</displayName>
            <value>parent_field</value>
          </configuration>
          <configuration name="limit_one">
            <displayName>Limit One</displayName>
            <value>1</value>
          </configuration>
        </configurationGroup>
        <configurationGroup name="visits">
          <displayName>Visits</displayName>
          <configuration name="display_name" locale="en_US">
            <displayName>Display Name</displayName>
            <value>Visits</value>
          </configuration>
          <configuration name="drop_empty">
            <displayName>Drop Empty</displayName>
            <value>2</value>
          </configuration>
          <configuration name="form">
            <displayName>Form</displayName>
            <value>followup_notes</value>
          </configuration>
          <configurationGroup name="joins">
            <displayName>Joins</displayName>
            <configurationGroup name="visit">
              <displayName>Visit</displayName>
              <configuration name="display_name" locale="en_US">
                <displayName>Display Name</displayName>
                <value>The Visit</value>
              </configuration>
              <configuration name="form">
                <displayName>Form</displayName>
                <value>visit</value>
              </configuration>
              <configurationGroup name="join_data">
                <displayName>Join Data</displayName>
                <configuration name="field">
                  <displayName>Field</displayName>
                  <value>visit</value>
                </configuration>
              </configurationGroup>
              <configuration name="join_style">
                <displayName>Join Style</displayName>
                <value>parent_field</value>
              </configuration>
              <configuration name="limit_one">
                <displayName>Limit One</displayName>
                <value>1</value>
              </configuration>
            </configurationGroup>
          </configurationGroup>
          <configurationGroup name="join_data">
            <displayName>Join Data</displayName>
            <configuration name="displaystyle">
              <displayName>Displaystyle</displayName>
              <value>default</value>
            </configuration>
          </configurationGroup>
          <configuration name="join_style">
            <displayName>Join Style</displayName>
            <value>child</value>
          </configuration>
          <configuration name="limit_one">
            <displayName>Limit One</displayName>
            <value>1</value>
          </configuration>
        </configurationGroup>
      </configurationGroup>
    </configurationGroup>
    <configurationGroup name="followup_clients" path="//modules/CustomReports/reports/followup_clients">
      <displayName>Export</displayName>
      <configurationGroup name="meta">
        <displayName>Meta</displayName>
        <configuration name="category">
          <displayName>Category</displayName>
          <value>VMMC Monthly Report</value>
        </configuration>
        <configuration name="description" locale="en_US">
          <displayName>Description</displayName>
          <value>Number of clients who returned for follow up</value>
        </configuration>
        <configuration name="display_name" locale="en_US">
          <displayName>Display Name</displayName>
          <value>Followup Clients</value>
        </configuration>
      </configurationGroup>
      <configuration name="relationship">
        <displayName>Relationship</displayName>
        <value>followup_clients</value>
      </configuration>
      <configurationGroup name="reporting_forms">
        <displayName>Reporting Forms</displayName>
        <configurationGroup name="primary_form">
          <displayName>Primary Form</displayName>
          <configurationGroup name="fields">
            <displayName>Fields</displayName>
            <configurationGroup name="facility">
              <displayName>Facility</displayName>
              <configuration name="enabled">
                <displayName>Enabled</displayName>
                <value>1</value>
              </configuration>
              <configuration name="header" locale="en_US">
                <displayName>Header</displayName>
                <value>Health Facility</value>
              </configuration>
              <configurationGroup name="limits">
                <displayName>Limits</displayName>
                <configurationGroup name="equals">
                  <displayName>Equals</displayName>
                  <configuration name="allow_pivot">
                    <displayName>Allow Pivot</displayName>
                    <value>1</value>
                  </configuration>
                  <configuration name="enabled">
                    <displayName>Enabled</displayName>
                    <value>1</value>
                  </configuration>
                  <configuration name="header" locale="en_US">
                    <displayName>Header</displayName>
                    <value>Health Facility</value>
                  </configuration>
                  <configuration name="pivot">
                    <displayName>Pivot</displayName>
                    <value>0</value>
                  </configuration>
                </configurationGroup>
              </configurationGroup>
              <configuration name="link_type">
                <displayName>Link Type</displayName>
                <value>link</value>
              </configuration>
            </configurationGroup>
            <configurationGroup name="id">
              <displayName>Id</displayName>
              <configuration name="enabled">
                <displayName>Enabled</displayName>
                <value>1</value>
              </configuration>
              <configuration name="header" locale="en_US">
                <displayName>Header</displayName>
                <value>Number of Clients</value>
              </configuration>
              <configuration name="link_type">
                <displayName>Link Type</displayName>
                <value>link</value>
              </configuration>
            </configurationGroup>
          </configurationGroup>
        </configurationGroup>
        <configurationGroup name="visits">
          <displayName>Visits</displayName>
          <configuration name="drop_empty">
            <displayName>Drop Empty</displayName>
            <value>0</value>
          </configuration>
          <configurationGroup name="fields">
            <displayName>Fields</displayName>
            <configurationGroup name="visit">
              <displayName>Visit</displayName>
              <configuration name="enabled">
                <displayName>Enabled</displayName>
                <value>1</value>
              </configuration>
              <configuration name="header" locale="en_US">
                <displayName>Header</displayName>
                <value>Visit</value>
              </configuration>
              <configurationGroup name="limits">
                <displayName>Limits</displayName>
                <configurationGroup name="equals">
                  <displayName>Equals</displayName>
                  <configuration name="allow_pivot">
                    <displayName>Allow Pivot</displayName>
                    <value>1</value>
                  </configuration>
                  <configuration name="enabled">
                    <displayName>Enabled</displayName>
                    <value>1</value>
                  </configuration>
                  <configuration name="header" locale="en_US">
                    <displayName>Header</displayName>
                    <value>Visit</value>
                  </configuration>
                  <configuration name="pivot">
                    <displayName>Pivot</displayName>
                    <value>0</value>
                  </configuration>
                </configurationGroup>
              </configurationGroup>
              <configuration name="link_type">
                <displayName>Link Type</displayName>
                <value>link</value>
              </configuration>
            </configurationGroup>
            <configurationGroup name="visit_date">
              <displayName>Visit Date</displayName>
              <configuration name="enabled">
                <displayName>Enabled</displayName>
                <value>1</value>
              </configuration>
              <configuration name="header" locale="en_US">
                <displayName>Header</displayName>
                <value>Visit Date</value>
              </configuration>
              <configurationGroup name="limits">
                <displayName>Limits</displayName>
                <configurationGroup name="greaterthan_equals">
                  <displayName>Greaterthan Equals</displayName>
                  <configuration name="allow_pivot">
                    <displayName>Allow Pivot</displayName>
                    <value>1</value>
                  </configuration>
                  <configuration name="enabled">
                    <displayName>Enabled</displayName>
                    <value>1</value>
                  </configuration>
                  <configuration name="header" locale="en_US">
                    <displayName>Header</displayName>
                    <value>Visit Date After</value>
                  </configuration>
                  <configuration name="pivot">
                    <displayName>Pivot</displayName>
                    <value>0</value>
                  </configuration>
                </configurationGroup>
                <configurationGroup name="lessthan">
                  <displayName>Lessthan</displayName>
                  <configuration name="allow_pivot">
                    <displayName>Allow Pivot</displayName>
                    <value>1</value>
                  </configuration>
                  <configuration name="enabled">
                    <displayName>Enabled</displayName>
                    <value>1</value>
                  </configuration>
                  <configuration name="header" locale="en_US">
                    <displayName>Header</displayName>
                    <value>Visit Date Before</value>
                  </configuration>
                  <configuration name="pivot">
                    <displayName>Pivot</displayName>
                    <value>0</value>
                  </configuration>
                </configurationGroup>
              </configurationGroup>
              <configuration name="link_type">
                <displayName>Link Type</displayName>
                <value>link</value>
              </configuration>
            </configurationGroup>
            <configurationGroup name="wound_delay">
              <displayName>Wound Delay</displayName>
              <configuration name="enabled">
                <displayName>Enabled</displayName>
                <value>1</value>
              </configuration>
              <configuration name="header" locale="en_US">
                <displayName>Header</displayName>
                <value>Followup Notes Delayed Wound Healing</value>
              </configuration>
              <configurationGroup name="limits">
                <displayName>Limits</displayName>
                <configurationGroup name="equals">
                  <displayName>Equals</displayName>
                  <configuration name="allow_pivot">
                    <displayName>Allow Pivot</displayName>
                    <value>1</value>
                  </configuration>
                  <configuration name="enabled">
                    <displayName>Enabled</displayName>
                    <value>1</value>
                  </configuration>
                  <configuration name="header" locale="en_US">
                    <displayName>Header</displayName>
                    <value>Delayed Wound Healing</value>
                  </configuration>
                  <configuration name="pivot">
                    <displayName>Pivot</displayName>
                    <value>0</value>
                  </configuration>
                </configurationGroup>
              </configurationGroup>
              <configuration name="link_type">
                <displayName>Link Type</displayName>
                <value>link</value>
              </configuration>
            </configurationGroup>
          </configurationGroup>
        </configurationGroup>
      </configurationGroup>
    </configurationGroup>
    <configurationGroup name="1401857346" path="//modules/CustomReports/reportViews/1401857346">
      <displayName>Export</displayName>
      <configuration name="description" locale="en_US">
        <displayName>Description</displayName>
        <value>Number of clients who returned for follow up</value>
      </configuration>
      <configuration name="disable">
        <displayName>Disable</displayName>
        <value>0</value>
      </configuration>
      <configuration name="display_name" locale="en_US">
        <displayName>Display Name</displayName>
        <value>Clients Returning for Followup</value>
      </configuration>
      <configuration name="display_order">
        <displayName>Display Order</displayName>
        <value>primary_form+facility,visits+visit,visits+visit_date,primary_form+id,visits+wound_delay</value>
      </configuration>
      <configurationGroup name="fields">
        <displayName>Fields</displayName>
        <configurationGroup name="primary_form+facility">
          <displayName>Primary Form Facility</displayName>
          <configuration name="aggregate">
            <displayName>Aggregate</displayName>
            <value>none</value>
          </configuration>
          <configuration name="enabled">
            <displayName>Enabled</displayName>
            <value>1</value>
          </configuration>
        </configurationGroup>
        <configurationGroup name="primary_form+id">
          <displayName>Primary Form Id</displayName>
          <configuration name="aggregate">
            <displayName>Aggregate</displayName>
            <value>count</value>
          </configuration>
          <configuration name="enabled">
            <displayName>Enabled</displayName>
            <value>1</value>
          </configuration>
        </configurationGroup>
        <configurationGroup name="visits+visit">
          <displayName>Visits Visit</displayName>
          <configuration name="aggregate">
            <displayName>Aggregate</displayName>
            <value>none</value>
          </configuration>
          <configuration name="enabled">
            <displayName>Enabled</displayName>
            <value>1</value>
          </configuration>
        </configurationGroup>
        <configurationGroup name="visits+visit_date">
          <displayName>Visits Visit Date</displayName>
          <configuration name="aggregate">
            <displayName>Aggregate</displayName>
            <value>none</value>
          </configuration>
          <configuration name="enabled">
            <displayName>Enabled</displayName>
            <value>1</value>
          </configuration>
        </configurationGroup>
      </configurationGroup>
      <configuration name="report">
        <displayName>Report</displayName>
        <value>followup_clients</value>
      </configuration>
      <configuration name="total">
        <displayName>Total</displayName>
        <value>0</value>
      </configuration>
    </configurationGroup>
  </configurationGroup>
</I2CEConfiguration>